LICENSE
MANIFEST.in
README.md
setup.py
PRWKV.egg-info/PKG-INFO
PRWKV.egg-info/SOURCES.txt
PRWKV.egg-info/dependency_links.txt
PRWKV.egg-info/requires.txt
PRWKV.egg-info/top_level.txt
prwkv/__init__.py
prwkv/modelrun.py
prwkv/rwkvrnnmodel.py
prwkv/rwkvtokenizer.py
prwkv/data/20B_tokenizer.json
prwkv/data/RWKV-4-14B.json
prwkv/data/RWKV-4-169M.json
prwkv/data/RWKV-4-1B5.json
prwkv/data/RWKV-4-3B.json
prwkv/data/RWKV-4-430M.json
prwkv/data/RWKV-4-7B.json