Metadata-Version: 2.1
Name: PRWKV
Version: 0.2.0
Summary: This project aims to make RWKV Accessible to everyone using a Hugging Face like OOP interface. Research done by BlinkDL.
Home-page: https://github.com/ArEnSc/Production-RWKV
Author: Michael Chung
Author-email: michael.chung@databites.ca
License: MIT
Platform: UNKNOWN
Classifier: Development Status :: 3 - Alpha
Classifier: Intended Audience :: Science/Research
Classifier: License :: OSI Approved :: MIT License
Classifier: Environment :: MacOS X
Classifier: Environment :: Win32 (MS Windows)
Classifier: Operating System :: POSIX :: Linux
Classifier: Operating System :: Microsoft :: Windows :: Windows 10
Classifier: Programming Language :: Python :: 3.9
License-File: LICENSE
